[{"CONTID":"B0003","CONTTYPE":"ROF","STATUS":"ex","LASTREPAIR":"19960531","SERIALNR":""},{"CONTID":"B0009","CONTTYPE":"MKL","STATUS":"ex","LASTREPAIR":"19981130","SERIALNR":""},{"CONTID":"B0016","CONTTYPE":"MKL","STATUS":"ex","LASTREPAIR":"19900101","SERIALNR":""},{"CONTID":"B0018","CONTTYPE":"MKL","STATUS":"ex","LASTREPAIR":"19900101","SERIALNR":""},{"CONTID":"B0019","CONTTYPE":"MKL","STATUS":"ex","LASTREPAIR":"19900101","SERIALNR":""},{"CONTID":"B0029","CONTTYPE":"MKL","STATUS":"ex","LASTREPAIR":"19900101","SERIALNR":""},{"CONTID":"B0054","CONTTYPE":"MKL","STATUS":"ex","LASTREPAIR":"19900101","SERIALNR":""},{"CONTID":"B0058","CONTTYPE":"MKL","STATUS":"ex","LASTREPAIR":"19900101","SERIALNR":""},{"CONTID":"B0059","CONTTYPE":"MKL","STATUS":"ex","LASTREPAIR":"19900101","SERIALNR":""},{"CONTID":"B0062","CONTTYPE":"MKL","STATUS":"ex","LASTREPAIR":"19900101","SERIALNR":""},{"CONTID":"B0065","CONTTYPE":"MKL","STATUS":"ex","LASTREPAIR":"19900101","SERIALNR":""},{"CONTID":"B0068","CONTTYPE":"MKL","STATUS":"ex","LASTREPAIR":"19900831","SERIALNR":""},{"CONTID":"B0081","CONTTYPE":"MKL","STATUS":"ex","LASTREPAIR":"19900101","SERIALNR":""},{"CONTID":"B0089","CONTTYPE":"MKL","STATUS":"ex","LASTREPAIR":"19900101","SERIALNR":""},{"CONTID":"B0091","CONTTYPE":"MKL","STATUS":"ex","LASTREPAIR":"19900101","SERIALNR":""},{"CONTID":"B0092","CONTTYPE":"MKL","STATUS":"ex","LASTREPAIR":"19900101","SERIALNR":""},{"CONTID":"B0094","CONTTYPE":"MKL","STATUS":"ex","LASTREPAIR":"19900101","SERIALNR":""},{"CONTID":"B0100","CONTTYPE":"MKL","STATUS":"ex","LASTREPAIR":"19900101","SERIALNR":""},{"CONTID":"B0104","CONTTYPE":"MKL","STATUS":"ex","LASTREPAIR":"20200101","SERIALNR":""},{"CONTID":"B0132","CONTTYPE":"MKL","STATUS":"ex","LASTREPAIR":"19900101","SERIALNR":""},{"CONTID":"B0133","CONTTYPE":"MKL","STATUS":"ex","LASTREPAIR":"19990322","SERIALNR":""},{"CONTID":"B0139","CONTTYPE":"MKL","STATUS":"ex","LASTREPAIR":"19900101","SERIALNR":""},{"CONTID":"B0140","CONTTYPE":"MKL","STATUS":"ex","LASTREPAIR":"19900101","SERIALNR":""},{"CONTID":"B0141","CONTTYPE":"MKL","STATUS":"ex","LASTREPAIR":"19990415","SERIALNR":""},{"CONTID":"B0142","CONTTYPE":"MKL","STATUS":"ex","LASTREPAIR":"19990412","SERIALNR":""},{"CONTID":"B0146","CONTTYPE":"MKL","STATUS":"ex","LASTREPAIR":"19900101","SERIALNR":""},{"CONTID":"B0161","CONTTYPE":"MKL","STATUS":"ex","LASTREPAIR":"19900101","SERIALNR":""},{"CONTID":"B0164","CONTTYPE":"HKL","STATUS":"ex","LASTREPAIR":"19900101","SERIALNR":""},{"CONTID":"B0166","CONTTYPE":"MKL","STATUS":"ex","LASTREPAIR":"19900101","SERIALNR":""},{"CONTID":"B0173","CONTTYPE":"ROT","STATUS":"ex","LASTREPAIR":"19950629","SERIALNR":""},{"CONTID":"B0176","CONTTYPE":"MKL","STATUS":"ex","LASTREPAIR":"19900101","SERIALNR":""},{"CONTID":"B0227","CONTTYPE":"MKL","STATUS":"ex","LASTREPAIR":"19900101","SERIALNR":""},{"CONTID":"B0238","CONTTYPE":"MKL","STATUS":"ex","LASTREPAIR":"19900101","SERIALNR":""},{"CONTID":"B0264","CONTTYPE":"MKL","STATUS":"ex","LASTREPAIR":"19990915","SERIALNR":""},{"CONTID":"B0289","CONTTYPE":"MKL","STATUS":"ex","LASTREPAIR":"19990921","SERIALNR":""},{"CONTID":"B0296","CONTTYPE":"MKL","STATUS":"ex","LASTREPAIR":"19900101","SERIALNR":""},{"CONTID":"B0300","CONTTYPE":"MKL","STATUS":"ex","LASTREPAIR":"20010103","SERIALNR":""},{"CONTID":"B0321","CONTTYPE":"SCA","STATUS":"ex","LASTREPAIR":"19900101","SERIALNR":""},{"CONTID":"B0331","CONTTYPE":"MKL","STATUS":"ex","LASTREPAIR":"19900101","SERIALNR":""},{"CONTID":"B0355","CONTTYPE":"MKL","STATUS":"ex","LASTREPAIR":"19900101","SERIALNR":""},{"CONTID":"B0392","CONTTYPE":"MKL","STATUS":"ex","LASTREPAIR":"19900101","SERIALNR":""},{"CONTID":"B0400","CONTTYPE":"MKL","STATUS":"ex","LASTREPAIR":"19900101","SERIALNR":""},{"CONTID":"B0460","CONTTYPE":"ROT","STATUS":"ex","LASTREPAIR":"19950629","SERIALNR":""},{"CONTID":"B0471","CONTTYPE":"MKL","STATUS":"ex","LASTREPAIR":"19900101","SERIALNR":""},{"CONTID":"B0483","CONTTYPE":"MKL","STATUS":"ex","LASTREPAIR":"19960501","SERIALNR":""},{"CONTID":"B0503","CONTTYPE":"MKL","STATUS":"ex","LASTREPAIR":"19900101","SERIALNR":""},{"CONTID":"B0505","CONTTYPE":"SCH","STATUS":"ex","LASTREPAIR":"19950629","SERIALNR":""},{"CONTID":"B0520","CONTTYPE":"MKL","STATUS":"ex","LASTREPAIR":"19900101","SERIALNR":""},{"CONTID":"B0547","CONTTYPE":"ROH","STATUS":"ex","LASTREPAIR":"19960418","SERIALNR":""},{"CONTID":"B0575","CONTTYPE":"MKL","STATUS":"ex","LASTREPAIR":"19900101","SERIALNR":""},{"CONTID":"B0588","CONTTYPE":"MKL","STATUS":"ex","LASTREPAIR":"19900101","SERIALNR":""},{"CONTID":"B0592","CONTTYPE":"MKL","STATUS":"ex","LASTREPAIR":"19900101","SERIALNR":""},{"CONTID":"B0621","CONTTYPE":"MKL","STATUS":"ex","LASTREPAIR":"19900101","SERIALNR":""},{"CONTID":"B0622","CONTTYPE":"MKL","STATUS":"ex","LASTREPAIR":"19900101","SERIALNR":""},{"CONTID":"B0630","CONTTYPE":"MKL","STATUS":"ex","LASTREPAIR":"19900101","SERIALNR":""},{"CONTID":"B0657","CONTTYPE":"R\u00dcG","STATUS":"ex","LASTREPAIR":"19970312","SERIALNR":""},{"CONTID":"B0661","CONTTYPE":"MKL","STATUS":"ex","LASTREPAIR":"19900101","SERIALNR":""},{"CONTID":"B0666","CONTTYPE":"MKL","STATUS":"ex","LASTREPAIR":"19900101","SERIALNR":""},{"CONTID":"B0667","CONTTYPE":"MKL","STATUS":"ex","LASTREPAIR":"20120106","SERIALNR":""},{"CONTID":"B0680","CONTTYPE":"ROK","STATUS":"ex","LASTREPAIR":"19970412","SERIALNR":""},{"CONTID":"B0696","CONTTYPE":"MKL","STATUS":"ex","LASTREPAIR":"19900101","SERIALNR":""},{"CONTID":"B0714","CONTTYPE":"ROK","STATUS":"ex","LASTREPAIR":"19960412","SERIALNR":"S 22305"},{"CONTID":"B0751","CONTTYPE":"MKL","STATUS":"ex","LASTREPAIR":"19900101","SERIALNR":""},{"CONTID":"B0757","CONTTYPE":"MKL","STATUS":"ex","LASTREPAIR":"19900101","SERIALNR":""},{"CONTID":"B0758","CONTTYPE":"MKL","STATUS":"ex","LASTREPAIR":"19900101","SERIALNR":""},{"CONTID":"B0766","CONTTYPE":"MKL","STATUS":"ex","LASTREPAIR":"19900101","SERIALNR":""},{"CONTID":"B0791","CONTTYPE":"ROT","STATUS":"ex","LASTREPAIR":"19950629","SERIALNR":""},{"CONTID":"B0864","CONTTYPE":"MKL","STATUS":"ex","LASTREPAIR":"19900101","SERIALNR":""},{"CONTID":"B0880","CONTTYPE":"SCHR","STATUS":"ex","LASTREPAIR":"20070820","SERIALNR":"101183"},{"CONTID":"B1031","CONTTYPE":"MKL","STATUS":"ex","LASTREPAIR":"19900101","SERIALNR":""},{"CONTID":"B1113","CONTTYPE":"ROH","STATUS":"ex","LASTREPAIR":"19960418","SERIALNR":""},{"CONTID":"B1151","CONTTYPE":"ROT","STATUS":"ex","LASTREPAIR":"19980903","SERIALNR":""},{"CONTID":"B1247","CONTTYPE":"SCH","STATUS":"ex","LASTREPAIR":"19960419","SERIALNR":""},{"CONTID":"B1500","CONTTYPE":"R\u00dcG","STATUS":"ex","LASTREPAIR":"19970312","SERIALNR":""},{"CONTID":"B1800","CONTTYPE":"ROH","STATUS":"ex","LASTREPAIR":"19960418","SERIALNR":""},{"CONTID":"B1950","CONTTYPE":"MKL","STATUS":"ex","LASTREPAIR":"19900101","SERIALNR":""},{"CONTID":"B6170","CONTTYPE":"R\u00dcG","STATUS":"ex","LASTREPAIR":"19970312","SERIALNR":""},{"CONTID":"B7014","CONTTYPE":"SCH","STATUS":"ex","LASTREPAIR":"19990315","SERIALNR":"62921"},{"CONTID":"B7042","CONTTYPE":"SCH","STATUS":"ex","LASTREPAIR":"19990315","SERIALNR":"62939"},{"CONTID":"B8004","CONTTYPE":"ROT","STATUS":"ex","LASTREPAIR":"19950629","SERIALNR":""},{"CONTID":"B8005","CONTTYPE":"ROT","STATUS":"ex","LASTREPAIR":"19950629","SERIALNR":""},{"CONTID":"B8006","CONTTYPE":"ROT","STATUS":"ex","LASTREPAIR":"19950629","SERIALNR":""},{"CONTID":"B8007","CONTTYPE":"R\u00dcG","STATUS":"ex","LASTREPAIR":"19970312","SERIALNR":""},{"CONTID":"B8008","CONTTYPE":"ROT","STATUS":"ex","LASTREPAIR":"19950629","SERIALNR":""},{"CONTID":"B8009","CONTTYPE":"MKL","STATUS":"ex","LASTREPAIR":"19900101","SERIALNR":""},{"CONTID":"B8013","CONTTYPE":"ROH","STATUS":"ex","LASTREPAIR":"19960418","SERIALNR":""},{"CONTID":"B9001","CONTTYPE":"MKL","STATUS":"ex","LASTREPAIR":"19900101","SERIALNR":""},{"CONTID":"B9002","CONTTYPE":"MKL","STATUS":"ex","LASTREPAIR":"19900101","SERIALNR":""},{"CONTID":"B9003","CONTTYPE":"ROT","STATUS":"ex","LASTREPAIR":"19950629","SERIALNR":""},{"CONTID":"B9010","CONTTYPE":"R\u00dcG","STATUS":"ex","LASTREPAIR":"19970312","SERIALNR":""},{"CONTID":"B9100","CONTTYPE":"ROH","STATUS":"ex","LASTREPAIR":"19960418","SERIALNR":""},{"CONTID":"B9110","CONTTYPE":"ROT","STATUS":"ex","LASTREPAIR":"19960412","SERIALNR":""},{"CONTID":"B9120","CONTTYPE":"ROT","STATUS":"ex","LASTREPAIR":"19960412","SERIALNR":""},{"CONTID":"B9130","CONTTYPE":"ROT","STATUS":"ex","LASTREPAIR":"19960412","SERIALNR":""},{"CONTID":"B9140","CONTTYPE":"ROH","STATUS":"ex","LASTREPAIR":"19960418","SERIALNR":""},{"CONTID":"B9180","CONTTYPE":"ROT","STATUS":"ex","LASTREPAIR":"19960412","SERIALNR":""},{"CONTID":"B9190","CONTTYPE":"ROH","STATUS":"ex","LASTREPAIR":"19960418","SERIALNR":""},{"CONTID":"B9200","CONTTYPE":"ROH","STATUS":"ex","LASTREPAIR":"19960418","SERIALNR":""},{"CONTID":"B9500","CONTTYPE":"SCH","STATUS":"ex","LASTREPAIR":"19960419","SERIALNR":""},{"CONTID":"B9600","CONTTYPE":"ROH","STATUS":"ex","LASTREPAIR":"19960418","SERIALNR":""},{"CONTID":"K0644","CONTTYPE":"MKL","STATUS":"ex","LASTREPAIR":"20111121","SERIALNR":""},{"CONTID":"K0701","CONTTYPE":"TRO","STATUS":"ex","LASTREPAIR":"","SERIALNR":""},{"CONTID":"S0001","CONTTYPE":"SCA","STATUS":"ex","LASTREPAIR":"20000405","SERIALNR":""},{"CONTID":"S0002","CONTTYPE":"SCH","STATUS":"ex","LASTREPAIR":"20000622","SERIALNR":"29834"},{"CONTID":"S0004","CONTTYPE":"S80","STATUS":"ex","LASTREPAIR":"20000405","SERIALNR":"BI5395"},{"CONTID":"S0007","CONTTYPE":"SCH","STATUS":"ex","LASTREPAIR":"20000405","SERIALNR":"50250"},{"CONTID":"S0013","CONTTYPE":"SCH","STATUS":"ex","LASTREPAIR":"20000405","SERIALNR":"26098"},{"CONTID":"S0030","CONTTYPE":"SCA","STATUS":"ex","LASTREPAIR":"20000405","SERIALNR":""},{"CONTID":"S0034","CONTTYPE":"SCA","STATUS":"ex","LASTREPAIR":"20000405","SERIALNR":""},{"CONTID":"S0036","CONTTYPE":"TRO","STATUS":"ex","LASTREPAIR":"20000405","SERIALNR":""},{"CONTID":"S0048","CONTTYPE":"SCH","STATUS":"ex","LASTREPAIR":"20000405","SERIALNR":""},{"CONTID":"S0054","CONTTYPE":"SCA","STATUS":"ex","LASTREPAIR":"20000405","SERIALNR":""},{"CONTID":"S0059","CONTTYPE":"SCH","STATUS":"ex","LASTREPAIR":"20000405","SERIALNR":"49903"},{"CONTID":"S0071","CONTTYPE":"SCH","STATUS":"ex","LASTREPAIR":"20000405","SERIALNR":""},{"CONTID":"S0075","CONTTYPE":"SCH","STATUS":"ex","LASTREPAIR":"20000405","SERIALNR":"49801"},{"CONTID":"S0079","CONTTYPE":"SCH","STATUS":"ex","LASTREPAIR":"20000405","SERIALNR":"49242"},{"CONTID":"S0085","CONTTYPE":"SCH","STATUS":"ex","LASTREPAIR":"20000405","SERIALNR":"47206"},{"CONTID":"S0102","CONTTYPE":"SCA","STATUS":"ex","LASTREPAIR":"20000504","SERIALNR":""},{"CONTID":"S0115","CONTTYPE":"SCH","STATUS":"ex","LASTREPAIR":"20000504","SERIALNR":"50230"},{"CONTID":"S0122","CONTTYPE":"SCH","STATUS":"ex","LASTREPAIR":"20000504","SERIALNR":"49795"},{"CONTID":"S0130","CONTTYPE":"SCH","STATUS":"ex","LASTREPAIR":"20000504","SERIALNR":"50756"},{"CONTID":"S0137","CONTTYPE":"SCA","STATUS":"ex","LASTREPAIR":"20000504","SERIALNR":""},{"CONTID":"S0140","CONTTYPE":"SCA","STATUS":"ex","LASTREPAIR":"20000504","SERIALNR":""},{"CONTID":"S0146","CONTTYPE":"SCA","STATUS":"ex","LASTREPAIR":"20000504","SERIALNR":""},{"CONTID":"S0147","CONTTYPE":"SCA","STATUS":"ex","LASTREPAIR":"20000504","SERIALNR":""},{"CONTID":"S0148","CONTTYPE":"SCA","STATUS":"ex","LASTREPAIR":"20000504","SERIALNR":""},{"CONTID":"S0160","CONTTYPE":"SCA","STATUS":"ex","LASTREPAIR":"20000504","SERIALNR":""},{"CONTID":"S0162","CONTTYPE":"SCH","STATUS":"ex","LASTREPAIR":"20000504","SERIALNR":"50745"},{"CONTID":"S0171","CONTTYPE":"SCH","STATUS":"ex","LASTREPAIR":"20000504","SERIALNR":"49808"},{"CONTID":"S0176","CONTTYPE":"SCH","STATUS":"ex","LASTREPAIR":"20000504","SERIALNR":"49798"},{"CONTID":"S0182","CONTTYPE":"SCH","STATUS":"ex","LASTREPAIR":"20000504","SERIALNR":"47216"},{"CONTID":"S0186","CONTTYPE":"SCA","STATUS":"ex","LASTREPAIR":"20000504","SERIALNR":"49245"},{"CONTID":"S0191","CONTTYPE":"SCA","STATUS":"ex","LASTREPAIR":"20000504","SERIALNR":""},{"CONTID":"S0194","CONTTYPE":"SCA","STATUS":"ex","LASTREPAIR":"20000504","SERIALNR":""},{"CONTID":"S0196","CONTTYPE":"SCA","STATUS":"ex","LASTREPAIR":"20000405","SERIALNR":""},{"CONTID":"S0197","CONTTYPE":"SCA","STATUS":"ex","LASTREPAIR":"20000504","SERIALNR":""},{"CONTID":"S0199","CONTTYPE":"SCA","STATUS":"ex","LASTREPAIR":"20000504","SERIALNR":""},{"CONTID":"S0209","CONTTYPE":"SCH","STATUS":"ex","LASTREPAIR":"20000504","SERIALNR":"89298"},{"CONTID":"S0211","CONTTYPE":"SCA","STATUS":"ex","LASTREPAIR":"20000504","SERIALNR":""},{"CONTID":"S0214","CONTTYPE":"SCA","STATUS":"ex","LASTREPAIR":"20000504","SERIALNR":""},{"CONTID":"S0216","CONTTYPE":"SCA","STATUS":"ex","LASTREPAIR":"20000504","SERIALNR":""},{"CONTID":"S0218","CONTTYPE":"SCA","STATUS":"ex","LASTREPAIR":"20000504","SERIALNR":""},{"CONTID":"S0233","CONTTYPE":"SCH","STATUS":"ex","LASTREPAIR":"20000504","SERIALNR":"49240"},{"CONTID":"S0243","CONTTYPE":"SCH","STATUS":"ex","LASTREPAIR":"20000504","SERIALNR":"47207"},{"CONTID":"S0245","CONTTYPE":"SCH","STATUS":"ex","LASTREPAIR":"20000504","SERIALNR":"29019"},{"CONTID":"S0246","CONTTYPE":"SCH","STATUS":"ex","LASTREPAIR":"20000504","SERIALNR":"50249"},{"CONTID":"S0248","CONTTYPE":"SCH","STATUS":"ex","LASTREPAIR":"20000504","SERIALNR":"49816"},{"CONTID":"S0254","CONTTYPE":"SCH","STATUS":"ex","LASTREPAIR":"20000504","SERIALNR":"47898"},{"CONTID":"S0257","CONTTYPE":"SCA","STATUS":"ex","LASTREPAIR":"20000504","SERIALNR":""},{"CONTID":"S0260","CONTTYPE":"SCA","STATUS":"ex","LASTREPAIR":"20000504","SERIALNR":""},{"CONTID":"S0273","CONTTYPE":"SCH","STATUS":"ex","LASTREPAIR":"20000504","SERIALNR":"49296"},{"CONTID":"S0275","CONTTYPE":"SCH","STATUS":"ex","LASTREPAIR":"20000504","SERIALNR":"50228"},{"CONTID":"S0276","CONTTYPE":"SCH","STATUS":"ex","LASTREPAIR":"20000504","SERIALNR":""},{"CONTID":"S0277","CONTTYPE":"SCH","STATUS":"ex","LASTREPAIR":"20000504","SERIALNR":"50739"},{"CONTID":"S0279","CONTTYPE":"SCA","STATUS":"ex","LASTREPAIR":"20000504","SERIALNR":""},{"CONTID":"S0280","CONTTYPE":"SCA","STATUS":"ex","LASTREPAIR":"20000504","SERIALNR":""},{"CONTID":"S0281","CONTTYPE":"SCA","STATUS":"ex","LASTREPAIR":"20000504","SERIALNR":""},{"CONTID":"S0282","CONTTYPE":"SCA","STATUS":"ex","LASTREPAIR":"20000504","SERIALNR":""},{"CONTID":"S0283","CONTTYPE":"SCA","STATUS":"ex","LASTREPAIR":"20000504","SERIALNR":""},{"CONTID":"S0284","CONTTYPE":"SCA","STATUS":"ex","LASTREPAIR":"20000504","SERIALNR":""},{"CONTID":"S0287","CONTTYPE":"SCA","STATUS":"ex","LASTREPAIR":"20000504","SERIALNR":""},{"CONTID":"S0289","CONTTYPE":"SCH","STATUS":"ex","LASTREPAIR":"20000504","SERIALNR":""},{"CONTID":"S0297","CONTTYPE":"SCA","STATUS":"ex","LASTREPAIR":"20000504","SERIALNR":"49812"},{"CONTID":"S0311","CONTTYPE":"SCH","STATUS":"ex","LASTREPAIR":"20000504","SERIALNR":"49244"},{"CONTID":"S0312","CONTTYPE":"SCA","STATUS":"ex","LASTREPAIR":"20000504","SERIALNR":""},{"CONTID":"S0314","CONTTYPE":"SCH","STATUS":"ex","LASTREPAIR":"20000504","SERIALNR":"50750"},{"CONTID":"S0315","CONTTYPE":"SCH","STATUS":"ex","LASTREPAIR":"20000504","SERIALNR":"67222"},{"CONTID":"S0316","CONTTYPE":"SCA","STATUS":"ex","LASTREPAIR":"20000504","SERIALNR":""},{"CONTID":"S0371","CONTTYPE":"SCH","STATUS":"ex","LASTREPAIR":"20000504","SERIALNR":""},{"CONTID":"S0374","CONTTYPE":"SCA","STATUS":"ex","LASTREPAIR":"20000504","SERIALNR":""},{"CONTID":"S0382","CONTTYPE":"SCA","STATUS":"ex","LASTREPAIR":"20000405","SERIALNR":""},{"CONTID":"S0426","CONTTYPE":"SCA","STATUS":"ex","LASTREPAIR":"20000405","SERIALNR":""},{"CONTID":"S0427","CONTTYPE":"SCA","STATUS":"ex","LASTREPAIR":"20000405","SERIALNR":""},{"CONTID":"S0429","CONTTYPE":"SCA","STATUS":"ex","LASTREPAIR":"20000405","SERIALNR":""},{"CONTID":"S0441","CONTTYPE":"SCA","STATUS":"ex","LASTREPAIR":"20000405","SERIALNR":""}]